pymob/py.typed
pymob/sim/config/__init__.pyi
types_pymob_guts_base-0.1.0.dist-info/METADATA
types_pymob_guts_base-0.1.0.dist-info/WHEEL
types_pymob_guts_base-0.1.0.dist-info/top_level.txt
types_pymob_guts_base-0.1.0.dist-info/RECORD
