Metadata-Version: 2.4
Name: types-pymob-guts-base
Version: 0.1.0
Summary: Stub‑only distribution that provides type hints for the pymob package.
Author-email: Florian Schunck <fluncki@protonmail.com>
License: MIT
Keywords: typing,stubs,pymob
Classifier: Programming Language :: Python :: 3
Classifier: Typing :: Typed
Classifier: Typing :: Stubs Only
Classifier: License :: OSI Approved :: MIT License
Classifier: Operating System :: OS Independent
Requires-Python: >=3.11
